errormaster/__init__.py
errormaster/errormaster.py
errormaster-2.0.0.dist-info/METADATA
errormaster-2.0.0.dist-info/WHEEL
errormaster-2.0.0.dist-info/RECORD
