Metadata-Version: 2.4
Name: errormaster
Version: 2.0.0
Summary: errorcatcher
Project-URL: Homepage, https://github.com/yourusername/fnsignal
Project-URL: Bug Tracker, https://github.com/yourusername/fnsignal/issues
Author-email: howShouldIChosseMyUsername <trademark2179@gmail.com>
License: MIT
Requires-Python: >=3.7
